rkstreamer/__init__.py
rkstreamer/__main__.py
rkstreamer/state.py
rkstreamer/controllers/__init__.py
rkstreamer/controllers/album.py
rkstreamer/controllers/enums.py
rkstreamer/controllers/patterns.py
rkstreamer/controllers/playlist.py
rkstreamer/controllers/queue.py
rkstreamer/controllers/song.py
rkstreamer/interfaces/__init__.py
rkstreamer/interfaces/_interface.py
rkstreamer/interfaces/controllers.py
rkstreamer/interfaces/database.py
rkstreamer/interfaces/models.py
rkstreamer/interfaces/network.py
rkstreamer/interfaces/patterns.py
rkstreamer/interfaces/player.py
rkstreamer/interfaces/provider.py
rkstreamer/interfaces/views.py
rkstreamer/models/__init__.py
rkstreamer/models/_model.py
rkstreamer/models/album.py
rkstreamer/models/data.py
rkstreamer/models/exceptions.py
rkstreamer/models/playlist.py
rkstreamer/models/song.py
rkstreamer/services/__init__.py
rkstreamer/services/album.py
rkstreamer/services/database.py
rkstreamer/services/network.py
rkstreamer/services/player.py
rkstreamer/services/playlist.py
rkstreamer/services/song.py
rkstreamer/types/__init__.py
rkstreamer/types/controllers.py
rkstreamer/types/misc.py
rkstreamer/types/models.py
rkstreamer/types/views.py
rkstreamer/utils/__init__.py
rkstreamer/utils/helper.py
rkstreamer/views/__init__.py
rkstreamer/views/album.py
rkstreamer/views/playlist.py
rkstreamer/views/song.py
rkstreamer-1.2.3.dist-info/LICENSE
rkstreamer-1.2.3.dist-info/METADATA
rkstreamer-1.2.3.dist-info/WHEEL
rkstreamer-1.2.3.dist-info/entry_points.txt
rkstreamer-1.2.3.dist-info/top_level.txt
rkstreamer-1.2.3.dist-info/RECORD
