Metadata-Version: 2.1
Name: rkstreamer
Version: 1.2.3
Summary: RK's CLI Music Player
Author-email: "Ray A." <ray@raysecure.ml>
License: MIT License
Project-URL: Github, https://github.com/rayep/rkstreamer
Classifier: Programming Language :: Python :: 3
Requires-Python: >=3.9
License-File: LICENSE
Requires-Dist: requests >=2.28.2
Requires-Dist: python-vlc >=3.0.18121
Requires-Dist: setuptools >=67.0.0
